Workbook

Sheet 0 Read Me
A1: Flipkart WiRED X — Campus Node Model
A2: Generated from the model by Model/make_workbook.py. Team ANAVRIN. Blue rows are sourced inputs; green rows are live formulas that recompute from the Inputs sheet. Nothing in this workbook is typed by hand, including the verification counts below.
A4: RELEASE CHECKS
A5: Layer | B5: Passed | C5: Defined | D5: Status | E5: Command | F5: Scope
A6: audit | B6: 378 | C6: 378 | D6: =IF(B6=C6,"PASS","FAIL") | E6: python3 Model/audit.py | F6: model against itself, incl. cross-module reconciliation
A7: docs | B7: 31 | C7: 31 | D7: =IF(B7=C7,"PASS","FAIL") | E7: python3 Model/verify_docs.py | F7: HANDOFF figures against the model
A8: spec | B8: 79 | C8: 79 | D8: =IF(B8=C8,"PASS","FAIL") | E8: python3 Model/verify_spec.py | F8: deck spec and build prompt against the model
A9: deck | B9: 184 | C9: 184 | D9: =IF(B9=C9,"PASS","FAIL") | E9: python3 Model/verify_deck.py | F9: the BUILT .pptx, presence and absence
A10: artefacts | B10: 28 | C10: 28 | D10: =IF(B10=C10,"PASS","FAIL") | E10: python3 Model/verify_artifacts.py | F10: workbook, notebooks, manifest, public data
A12: ALL FIVE LAYERS PASSED on the last recorded run.

Sheet 1 Inputs
A1: Inputs and policy constants
A2: Every contested policy constant lives in Model/params.py and is imported everywhere else. A value redeclared outside params.py fails the audit.
A4: Parameter | B4: Value | C4: Unit | D4: Tier | E4: Source / derivation
A5: Cluster volume | B5: 1400 | C5: orders/day | D5: T1 | E5: JM Ex.29 observed 1,334–1,487 band
A6: Campus gates per node | B6: 3 | C6: gates | D6: D | E6: params.CAMPUSES_PER_NODE
A7: Active academic months | B7: 8.5 | C7: months/yr | D7: T1 | E7: institutional calendars
A8: Revenue take rate | B8: 0.1941 | C8: % of GOV | D8: T1 | E8: JM Financial, Eternal FY26E
A9: Store fixed cost | B9: 902000 | C9: Rs/month | D9: T1 | E9: JM Financial Exhibit 13
A10: Store ops per order | B10: 39 | C10: Rs/order | D10: T2 | E10: pick, pack, warehousing
A11: Packaging per order | B11: 12 | C11: Rs/order | D11: T2 | E11: packaging + support
A12: Unallocated residual | B12: 12.3054 | C12: Rs/order | D12: D | E12: implied variable less itemised
A13: City gig leg | B13: 14.249352 | C13: Rs/order | D13: D | E13: sla.py, volume-weighted across demand bands
A14: In-gate roster leg | B14: 3.3638729 | C14: Rs/order | D14: D | E14: fleet_mix.plan_roster(), fixed roster / volume
A15: NWC days | B15: 14 | C15: days | D15: T1 | E15: Eternal Q1FY27, on NOV not COGS
A16: Capex midpoint | B16: 23500000 | C16: Rs | D16: T2 | E16: band midpoint
... A18: Node life | B18: 60 | C18: months | D18: D | E18: must outlive its own payback
A19: PG demand evidence gate | B19: FALSE | C19: TRUE/FALSE | D19: P | E19: opens only after site evidence is approved
A20: PG verified occupied student beds | B20: 0 | C20: beds | D20: P | E20: occupied STUDENT beds inside the served radius
A21: PG active-user penetration | B21: 0 | C21: % | D21: P | E21: pilot-observed active users / occupied student beds
A22: PG gross AOV | B22: 0 | C22: Rs/order | D22: P | E22: pilot-observed; zero means not evidenced
A23: PG common-drop share | B23: 0 | C23: % | D23: P | E23: share served at reception, warden desk or locker
A24: PG break retention | B24: 0 | C24: % of term | D24: P | E24: PG demand persisting through the academic break
A25: Hostel term volume in PG scenario | B25: 1400 | C25: orders/day | D25: P | E25: capacity already consumed by the hostel base
A26: PG orders per active user per day | B26: 0.12 | C26: orders/day | D26: T1 | E26: Blinkit 3.6/month / 30; no captive-campus uplift
A27: PG doorstep last mile | B27: 26.873898 | C27: Rs/order | D27: D | E27: cost_stack Type B urban PG geometry
A28: PG common-drop last mile | B28: 23.952822 | C28: Rs/order | D28: D | E28: cost_stack Type B common-drop geometry
A29: NOV / GOV | B29: 0.791 | C29: x | D29: T1 | E29: Blinkit FY26E
A30: Term days | B30: 258.54167 | C30: days/year | D30: D | E30: 365 x active academic months / 12
A31: Break days | B31: 106.45833 | C31: days/year | D31: D | E31: 365 - term days
A32: Hostel comparison AOV | B32: 729.38346 | C32: Rs/order | D32: D | E32: basket at the 30% non-grocery floor

Sheet 2 Fulfilment
A1: Fulfilment — two legs, two cost structures
A2: The city leg is gig, bought per trip and divided by batch, so it varies by demand band. The in-gate leg is a fixed roster divided by daily volume, so it is FLAT across bands. That flatness is the argument for rostering.
A4: Demand band | B4: Hours | C4: Multiplier | D4: % of orders | E4: Orders/hr | F4: Batch | G4: City Rs/order | H4: In-gate Rs/order | I4: Total Rs/order | J4: SLA min
A5: Peak (late evening, exam windows) | B5: 4 | C5: 4 | D5: 0.62745098 | E5: 103.7 | F5: 10 | G5: 5.12 | H5: 3.36 | I5: 8.48 | J5: 27.1
A6: Normal | B6: 8 | C6: 1 | D6: 0.31372549 | E6: 25.9 | F6: 2 | G6: 25.59 | H6: 3.36 | I6: 28.95 | J6: 21.6
A7: Trough (early morning, class hrs) | B7: 6 | C7: 0.25 | D7: 0.058823529 | E7: 6.5 | F7: 1 | G7: 51.18 | H7: 3.36 | I7: 54.54 | J7: 25.7
A9: VOLUME-WEIGHTED LAST MILE | G9: =SUMPRODUCT(D5:D7,G5:G7) | H9: =H5 | I9: =G9+H9
A10: Standard 2–3 km residential zone | I10: 42
A11: Saving vs a standard zone | I11: =1-I9/I10
A14: ROSTER — base case is PER GATE
A15: per gate (467/day) | B15: 2 | C15: runners | D15: alpha 87% | E15: Rs3.36/order
A16: pooled across 3 gates (UPSIDE, not the plan) | B16: 7 | C16: runners | D16: alpha 100% | E16: Rs2.88/order — Rs0.48 better, conditional on cross-gate movement

Sheet 3 Unit Economics
A1: Unit economics and the AOV thresholds
A2: Two day-count conventions are both in use and both correct. The deck spine carries the fixed base across twelve 30-day months; the returns model uses a 365-day year. The gap is stated rather than smoothed away.
A4: Metric | B4: Value | C4: Unit | D4: Reading
A5: Variable cost per order | B5: 80.92 | C5: Rs | D5: last mile + store ops + packaging + residual
A6: Active days per year | B6: 258.5 | C6: days | D6: 365 x 8.5/12
A7: Annual orders, term-only | B7: 361958 | C7: orders | D7: returns basis
A8: Breakeven AOV — 365-day returns basis | B8: 571 | C8: Rs | D8: ROCE = 0
A9: Breakeven AOV — 30-day deck spine | B9: 573 | C9: Rs | D9: the deck headline
A10: Day-count gap between the two | B10: 2.14 | C10: Rs | D10: asserted, not smoothed
A11: AOV at the 40% external benchmark | B11: 755 | C11: Rs | D11: Eternal's disclosed return, not Flipkart's
A12: Premium over breakeven | B12: 184 | C12: Rs | D12: what the basket lever must buy
A13: Non-grocery share the benchmark implies | B13: 32.3 | C13: % of GOV | D13: inside the 30-40% range Swiggy discloses

Sheet 4 Returns
A1: Return on capital, DuPont and the scenarios
A2: ROCE = EBIT/CE = margin leg x turnover leg. Capital employed is capex plus working capital on the adopted 14-day-on-NOV construct.
A4: Line | B4: Value | C4: Unit | D4: Note
A5: Capex, band midpoint | B5: 235 | C5: Rs lakh
A6: Working capital | B6: 88.9 | C6: Rs lakh | D6: 14 NWC days on NOV
A7: Capital employed | B7: 323.9 | C7: Rs lakh | D7: capex + working capital
A8: DuPont margin leg | B8: 4.74 | C8: % | D8: at the benchmark AOV
A9: DuPont turnover leg | B9: 8.44 | C9: x | D9: the node's own turnover on CE
A10: Like-for-like asset turn | B10: 6.93 | C10: x | D10: common AOV Rs450, isolates density x calendar
A11: IRR at the benchmark AOV | B11: 34.4 | C11: % | D11: 5-year life, 3-month ramp
A13: Scenario | B13: AOV | C13: Margin | D13: Turn | E13: ROCE | F13: Payback mo
A14: Underwritten (AOV at breakeven) | B14: 571 | C14: 0 | D14: 6.38 | E14: 0 | F14: —
A15: Basket at 30% non-grocery | B15: 729 | C15: 4.22 | D15: 8.15 | E15: 34.4 | F15: 25
A16: Basket at 40% non-grocery | B16: 842 | C16: 6.25 | D16: 9.41 | E16: 58.8 | F16: 15
A17: Basket at 30%, volume -30% | B17: 729 | C17: 2.46 | D17: 5.71 | E17: 14 | F17: 62
A19: THE LIMIT: at a 30% basket with volume -30%, ROCE is 14.0% and payback runs to 62 months against a 60-month life. The node does not pay back within its life under that combination, which is why day 90 measures volume first.

Sheet 5 Dead Zone
A1: The academic dead zone, priced
A2: A 3.5-month break with no students. Five strategies, one basis. Repurpose fills the node from the adjacent catchment rather than mothballing it.
A4: Restart credit state | B4: Working capital | C4: Note
A5: credit intact | B5: 0 | C5: suppliers resume terms; the rebuild is payables-funded
A6: 30-day reset | B6: 37.8 | C6: partially self-funded while terms re-establish
A7: full reset (ADOPTED) | B7: 75.5 | C7: the whole 60-day cycle self-funded — the downside
A9: Working-capital constructs
A10: NWC days x NOV (14d) | B10: 88.9 | C10: ADOPTED
A11: 12-day steady state | B11: 76.2 | C11: sensitivity
A12: COGS x 18 days | B12: 116.4 | C12: REJECTED — double-counts the netting

Sheet 6 Risks
A1: Priced shocks, against the deck spine
A2: Each shock is re-solved for the AOV it would require, on the same D2-consistent basis as the spine. One combined case moves two variables together.
A4: Shock | B4: Breakeven AOV | C4: Basis
A5: Volume -30% | B5: 640 | C5: thinner fixed-base absorption
A6: Shrinkage, upper bound | B6: 615 | C6: 1.8% of NOV
A7: Gig social-security levy | B7: 588 | C7: 201st Parliamentary report
A8: Calendar fragmentation | B8: 582 | C8: shape of the break, not its length
A10: Deck spine for comparison: Rs573

Sheet 7 District Screen
A1: The site screen — districts, not sites
A2: A desktop screen over the AISHE register. It ranks candidates; siting still runs the cluster test on the ground.
A4: Step | B4: Count | C4: Note
A5: Institutions in the register | B5: 72352 | C5: AISHE, as on 28-8-2026
A6: Colleges only | B6: 54014 | C6: colleges
A7: Urban colleges | B7: 21000 | C7: urban flag
A8: Districts passing four criteria | B8: 111 | C8: of 765 (State, District) pairs
A9: Uncontested | B9: 9 | C9: the screen's own floor: 6-7 urban colleges
A10: Contested | B10: 22
A11: Stacked | B11: 80

Sheet 8 Verification
A1: How this package checks itself
A2: 5 verification layers plus four source scans. Absence checks matter as much as presence: ones: a superseded figure in a panel nothing reads is invisible to a positive check.
A4: Guard | B4: What it catches
A5: params.py | B5: a contested policy constant defined more than once
A6: verify_artifacts.py | B6: a stale figure in the workbook, notebooks or asset manifest
A7: recon(a, b) | B7: two modules computing the same quantity under different policies
A8: phrase bans | B8: wording the deck must not contain, including attribution
A9: superseded-value bans | B9: a pre-correction figure surviving in any panel
A10: duplicate-registration guard | B10: a check registered twice, inflating the count
A11: stale-basis scan | B11: a superseded value used as a literal cost basis, defaults included
A12: document scan | B12: a superseded figure in HANDOFF, spec, build prompt or README
A13: release.py | B13: build - verify - capture - stamp - re-verify the exact stamped file

Sheet 9 PG Adjacency
A1: PG adjacency — evidence-gated demand and capacity
A2: The hostel-only base case is unchanged. PG demand enters only after the evidence gate opens, and only into spare term capacity or available break-period capacity. Edit the gold pilot inputs on 1 Inputs; every output below is a live formula.
A4: CONFIGURED SCENARIO — ZERO UNTIL THE PILOT INPUTS ARE EVIDENCED
A5: Metric | B5: Value | C5: Unit | D5: Decision reading
A6: PG demand evidence status | B6: =IF(AND('1 Inputs'!$B$19=TRUE,'1 Inputs'!$B$20>0,'1 Inputs'!$B$21>0,'1 Inputs'!$B$22>0),"OPEN","CLOSED") | D6: CLOSED means PG contributes zero to every published return
A7: Gross PG demand | B7: =IF(AND('1 Inputs'!$B$19=TRUE,'1 Inputs'!$B$20>0,'1 Inputs'!$B$21>0,'1 Inputs'!$B$22>0),'1 Inputs'!$B$20*'1 Inputs'!$B$21*'1 Inputs'!$B$26,0) | C7: orders/day | D7: verified beds × active-user penetration × frequency
A8: Spare term capacity | B8: =MAX(0,'1 Inputs'!$B$5-'1 Inputs'!$B$25) | C8: orders/day | D8: PG is not added above the store working ceiling
A9: PG admitted in term | B9: =MIN(B7,B8) | C9: orders/day | D9: the lower of evidenced demand and spare capacity
A10: PG overflow / capacity trigger | B10: =MAX(0,B7-B9) | C10: orders/day | D10: requires capacity expansion or remains unserved
A11: PG admitted in academic break | B11: =MIN('1 Inputs'!$B$5,B7*'1 Inputs'!$B$24) | C11: orders/day | D11: zero until break retention is measured
A12: Weighted PG last mile | B12: =(1-'1 Inputs'!$B$23)*'1 Inputs'!$B$27+'1 Inputs'!$B$23*'1 Inputs'!$B$28 | C12: Rs/order | D12: doorstep/common-drop mix
A13: PG contribution per order | B13: =IF('1 Inputs'!$B$22>0,'1 Inputs'!$B$8*'1 Inputs'!$B$22-B12-'1 Inputs'!$B$10-'1 Inputs'!$B$11-'1 Inputs'!$B$12,0) | C13: Rs/order | D13: same take rate and store-cost basis as the core model
A14: Annual incremental PG orders | B14: =B9*'1 Inputs'!$B$30+B11*'1 Inputs'!$B$31 | C14: orders/year | D14: term spare capacity plus measured break retention
A15: Incremental PG EBIT | B15: =B14*B13 | C15: Rs/year | D15: before any capacity-expansion capex
A16: Incremental PG working capital | B16: =MAX(B9,B11)*'1 Inputs'!$B$22*'1 Inputs'!$B$29*'1 Inputs'!$B$15 | C16: Rs | D16: 14 NWC days on incremental NOV
A17: Base EBIT at configured hostel volume | B17: =('1 Inputs'!$B$8*'1 Inputs'!$B$32-'1 Inputs'!$B$13-'1 Inputs'!$B$14-'1 Inputs'!$B$10-'1 Inputs'!$B$11-'1 Inputs'!$B$12)*'1 Inputs'!$B$25*'1 Inputs'!$B$30-'1 Inputs'!$B$9*12 | C17: Rs/year | D17: 30% non-grocery AOV comparison basis
A18: Pro-forma node ROCE | B18: =(B17+B15)/('1 Inputs'!$B$16+'1 Inputs'!$B$15*'1 Inputs'!$B$5*'1 Inputs'!$B$32*'1 Inputs'!$B$29+B16) | C18: % | D18: PG changes the return only after the evidence gate opens
A21: NORMALISED CAPACITY SENSITIVITY — PER 1,000 VERIFIED OCCUPIED STUDENT BEDS
A22: Active-user penetration | B22: Hostel orders/day | C22: Gross PG orders/day | D22: Spare capacity | E22: PG served | F22: PG overflow
A23: 0.1 | B23: 1000 | C23: =1000*A23*'1 Inputs'!$B$26 | D23: =MAX(0,'1 Inputs'!$B$5-B23) | E23: =MIN(C23,D23) | F23: =MAX(0,C23-E23)
A24: 0.1 | B24: 1200 | C24: =1000*A24*'1 Inputs'!$B$26 | D24: =MAX(0,'1 Inputs'!$B$5-B24) | E24: =MIN(C24,D24) | F24: =MAX(0,C24-E24)
A25: 0.1 | B25: 1400 | C25: =1000*A25*'1 Inputs'!$B$26 | D25: =MAX(0,'1 Inputs'!$B$5-B25) | E25: =MIN(C25,D25) | F25: =MAX(0,C25-E25)
A26: 0.25 | B26: 1000 | C26: =1000*A26*'1 Inputs'!$B$26 | D26: =MAX(0,'1 Inputs'!$B$5-B26) | E26: =MIN(C26,D26) | F26: =MAX(0,C26-E26)
A27: 0.25 | B27: 1200 | C27: =1000*A27*'1 Inputs'!$B$26 | D27: =MAX(0,'1 Inputs'!$B$5-B27) | E27: =MIN(C27,D27) | F27: =MAX(0,C27-E27)
A28: 0.25 | B28: 1400 | C28: =1000*A28*'1 Inputs'!$B$26 | D28: =MAX(0,'1 Inputs'!$B$5-B28) | E28: =MIN(C28,D28) | F28: =MAX(0,C28-E28)
A29: 0.4 | B29: 1000 | C29: =1000*A29*'1 Inputs'!$B$26 | D29: =MAX(0,'1 Inputs'!$B$5-B29) | E29: =MIN(C29,D29) | F29: =MAX(0,C29-E29)
A30: 0.4 | B30: 1200 | C30: =1000*A30*'1 Inputs'!$B$26 | D30: =MAX(0,'1 Inputs'!$B$5-B30) | E30: =MIN(C30,D30) | F30: =MAX(0,C30-E30)
A31: 0.4 | B31: 1400 | C31: =1000*A31*'1 Inputs'!$B$26 | D31: =MAX(0,'1 Inputs'!$B$5-B31) | E31: =MIN(C31,D31) | F31: =MAX(0,C31-E31)
A34: PG UNIT ECONOMICS — EXISTING MODEL AOV REFERENCES, NOT A FORECAST
A35: AOV reference | B35: AOV | C35: Common-drop share | D35: Last mile | E35: Contribution/order | F35: Reading
A36: Minutes current midpoint | B36: 450 | C36: 0 | D36: =(1-C36)*'1 Inputs'!$B$27+C36*'1 Inputs'!$B$28 | E36: ='1 Inputs'!$B$8*B36-D36-'1 Inputs'!$B$10-'1 Inputs'!$B$11-'1 Inputs'!$B$12 | F36: =IF(E36>0,"positive before fixed cost","does not cover variable cost")
A37: Minutes current midpoint | B37: 450 | C37: 0.5 | D37: =(1-C37)*'1 Inputs'!$B$27+C37*'1 Inputs'!$B$28 | E37: ='1 Inputs'!$B$8*B37-D37-'1 Inputs'!$B$10-'1 Inputs'!$B$11-'1 Inputs'!$B$12 | F37: =IF(E37>0,"positive before fixed cost","does not cover variable cost")
A38: Minutes current midpoint | B38: 450 | C38: 1 | D38: =(1-C38)*'1 Inputs'!$B$27+C38*'1 Inputs'!$B$28 | E38: ='1 Inputs'!$B$8*B38-D38-'1 Inputs'!$B$10-'1 Inputs'!$B$11-'1 Inputs'!$B$12 | F38: =IF(E38>0,"positive before fixed cost","does not cover variable cost")
A39: Campus spine breakeven | B39: 573.0961 | C39: 0 | D39: =(1-C39)*'1 Inputs'!$B$27+C39*'1 Inputs'!$B$28 | E39: ='1 Inputs'!$B$8*B39-D39-'1 Inputs'!$B$10-'1 Inputs'!$B$11-'1 Inputs'!$B$12 | F39: =IF(E39>0,"positive before fixed cost","does not cover variable cost")
A40: Campus spine breakeven | B40: 573.0961 | C40: 0.5 | D40: =(1-C40)*'1 Inputs'!$B$27+C40*'1 Inputs'!$B$28 | E40: ='1 Inputs'!$B$8*B40-D40-'1 Inputs'!$B$10-'1 Inputs'!$B$11-'1 Inputs'!$B$12 | F40: =IF(E40>0,"positive before fixed cost","does not cover variable cost")
A41: Campus spine breakeven | B41: 573.0961 | C41: 1 | D41: =(1-C41)*'1 Inputs'!$B$27+C41*'1 Inputs'!$B$28 | E41: ='1 Inputs'!$B$8*B41-D41-'1 Inputs'!$B$10-'1 Inputs'!$B$11-'1 Inputs'!$B$12 | F41: =IF(E41>0,"positive before fixed cost","does not cover variable cost")
A42: 30% non-grocery basket | B42: 729.38346 | C42: 0 | D42: =(1-C42)*'1 Inputs'!$B$27+C42*'1 Inputs'!$B$28 | E42: ='1 Inputs'!$B$8*B42-D42-'1 Inputs'!$B$10-'1 Inputs'!$B$11-'1 Inputs'!$B$12 | F42: =IF(E42>0,"positive before fixed cost","does not cover variable cost")
A43: 30% non-grocery basket | B43: 729.38346 | C43: 0.5 | D43: =(1-C43)*'1 Inputs'!$B$27+C43*'1 Inputs'!$B$28 | E43: ='1 Inputs'!$B$8*B43-D43-'1 Inputs'!$B$10-'1 Inputs'!$B$11-'1 Inputs'!$B$12 | F43: =IF(E43>0,"positive before fixed cost","does not cover variable cost")
A44: 30% non-grocery basket | B44: 729.38346 | C44: 1 | D44: =(1-C44)*'1 Inputs'!$B$27+C44*'1 Inputs'!$B$28 | E44: ='1 Inputs'!$B$8*B44-D44-'1 Inputs'!$B$10-'1 Inputs'!$B$11-'1 Inputs'!$B$12 | F44: =IF(E44>0,"positive before fixed cost","does not cover variable cost")
